solari/__init__.py
solari/solari.py
solari/exceptions/__init__.py
solari/exceptions/leona_exceptions.py
solari/stats/__init__.py
solari/stats/champions_rate_stats.py
solari/stats/champions_stats.py
solari/stats/items_rate_stats.py
solari/stats/player_rates.py
solari/stats/player_stats.py
solari/stats/stats_managers.py
solari/stats/stats_types.py
solari-0.2.0.dist-info/LICENSE
solari-0.2.0.dist-info/METADATA
solari-0.2.0.dist-info/WHEEL
solari-0.2.0.dist-info/top_level.txt
solari-0.2.0.dist-info/RECORD
