Metadata-Version: 2.1
Name: solari
Version: 0.2.0
Summary: Library for high level statistical analysis on bulk match data
Home-page: https://github.com/Canisback/solari
Author: Canisback
Author-email: canisback@gmail.com
License: UNKNOWN
Keywords: Riot Games API,Riot API,stats,League of Legends
Platform: UNKNOWN
Requires-Python: >=3.8
License-File: LICENSE
Requires-Dist: pandas
Requires-Dist: sortedcontainers
